<?xml version="1.0" encoding="UTF-8"?>
<objects serializationModel="Studio.02.02.00">
	<object class="AudioFile" id="{80fe85db-a758-4f53-bbd9-b19a012cd1c0}">
		<property name="assetPath">
			<value>interface 界面/PickUp/放好/把矿石放在背包里－xh20070419.wav</value>
		</property>
		<property name="frequencyInKHz">
			<value>22.0499992</value>
		</property>
		<property name="channelCount">
			<value>1</value>
		</property>
		<property name="length">
			<value>0.84752834467120186</value>
		</property>
		<relationship name="masterAssetFolder">
			<destination>{649769e7-58d7-417a-8dda-378767d03798}</destination>
		</relationship>
	</object>
</objects>
